make_cv/UR2latex.py
make_cv/UR2latex_far.py
make_cv/__init__.py
make_cv/add_validation.py
make_cv/advising2latex_far.py
make_cv/bib2latex_far.py
make_cv/bib_add_citations.py
make_cv/bib_add_keywords.py
make_cv/bib_add_student_markers.py
make_cv/bib_get_entries_google.py
make_cv/bib_get_entries_orcid.py
make_cv/bib_get_entries_scopus.py
make_cv/bib_get_entries_uspto.py
make_cv/copy_with_timestamp.py
make_cv/create_config.py
make_cv/editor2excel_publons.py
make_cv/global_prefs.py
make_cv/grants2latex_far.py
make_cv/invited_text2bib.bash
make_cv/make_cv.py
make_cv/make_far.py
make_cv/make_nsfcoa.py
make_cv/make_web.py
make_cv/personal_awards2latex.py
make_cv/personal_awards2latex_far.py
make_cv/props2latex_far.py
make_cv/reviews2excel_orcid.py
make_cv/reviews2excel_publons.py
make_cv/reviews2latex_far.py
make_cv/service2latex.py
make_cv/service2latex_far.py
make_cv/shortformteaching.py
make_cv/stringprotect.py
make_cv/student_awards2latex.py
make_cv/student_awards2latex_far.py
make_cv/teaching2latex.py
make_cv/teaching2latex_far.py
make_cv/thesis2latex_far.py
make_cv/files/Awards/personal awards data.xlsx
make_cv/files/Awards/student awards data.xlsx
make_cv/files/Proposals & Grants/proposals & grants.xlsx
make_cv/files/Scholarship/current student data.xlsx
make_cv/files/Scholarship/scholarship.bib
make_cv/files/Scholarship/thesis data.xlsx
make_cv/files/Service/professional development data.xlsx
make_cv/files/Service/reviews data.xlsx
make_cv/files/Service/service data.xlsx
make_cv/files/Service/undergraduate research data.xlsx
make_cv/files/Teaching/teaching evaluation data.xlsx
make_cv/files/make_cv/2Page/nsf2page.tex
make_cv/files/make_cv/ABET/cv.tex
make_cv/files/make_cv/ABET/make_cv.cfg
make_cv/files/make_cv/ABET/settings.sty
make_cv/files/make_cv/CV/cv.tex
make_cv/files/make_cv/CV/make_cv.cfg
make_cv/files/make_cv/CV/settings.sty
make_cv/files/make_cv/Collaborators/make_cv.cfg
make_cv/files/make_cv/FAR/far.tex
make_cv/files/make_cv/FAR/far_header.tex
make_cv-0.8.1.dist-info/METADATA
make_cv-0.8.1.dist-info/WHEEL
make_cv-0.8.1.dist-info/entry_points.txt
make_cv-0.8.1.dist-info/licenses/LICENSE.md
make_cv-0.8.1.dist-info/RECORD
