Metadata-Version: 2.4
Name: make_cv
Version: 0.8.1
Summary: A package to make a faculty c.v. using python and LaTeX
Project-URL: Homepage, https://github.com/bhelenbr/make_cv
Project-URL: Issues, https://github.com/bhelenbr/make_cv/issues
Author-email: Brian Helenbrook <brian.helenbrook@gmail.com>
License-File: LICENSE.md
Classifier: Development Status :: 3 - Alpha
Classifier: License :: OSI Approved :: GNU General Public License v3 (GPLv3)
Classifier: Operating System :: OS Independent
Classifier: Programming Language :: Python :: 3
Requires-Python: >=3.8
Requires-Dist: beautifulsoup4
Requires-Dist: bibtexautocomplete>=1.4.0
Requires-Dist: bibtexparser<2.0.0
Requires-Dist: openpyxl
Requires-Dist: pandas
Requires-Dist: pybliometrics
Requires-Dist: pylatexenc
Requires-Dist: requests
Requires-Dist: scholarly
Requires-Dist: selenium
Requires-Dist: webdriver-manager
Requires-Dist: xlsxwriter
